styletext.py
styletext-1.0.1.dist-info/METADATA
styletext-1.0.1.dist-info/WHEEL
styletext-1.0.1.dist-info/licenses/LICENSE
styletext-1.0.1.dist-info/RECORD
