Metadata-Version: 2.4
Name: styletext
Version: 1.0.1
Summary: A Python library providing a styleText function similar to Node.js util.styleText
Project-URL: Homepage, https://github.com/goggle555/styletext-py
Project-URL: Repository, https://github.com/goggle555/styletext-py
Project-URL: Issues, https://github.com/goggle555/styletext-py/issues
Author-email: goggle555 <goggle555@fives.tech>
License: MIT
License-File: LICENSE
Keywords: ansi,color,console,formatting,nodejs,style,terminal,text
Classifier: Development Status :: 5 - Production/Stable
Classifier: Intended Audience :: Developers
Classifier: License :: OSI Approved :: MIT License
Classifier: Operating System :: OS Independent
Classifier: Programming Language :: Python :: 3
Classifier: Programming Language :: Python :: 3.11
Classifier: Programming Language :: Python :: 3.12
Classifier: Programming Language :: Python :: 3.13
Classifier: Topic :: Software Development :: Libraries :: Python Modules
Classifier: Topic :: Terminals
Requires-Python: >=3.11
